{
    "inputFile": "/home/lindsay/xeolabs/xeokit-model-conversion-tests-sep8/inputFiles/BIM1/BIM1841.ifc",
    "converterApplication": "ifc2gltfcxconverter",
    "converterApplicationVersion": "3.0.7",
    "conversionDate": "2023-12-24 19:48:15",
    "gltfOutFiles": [
        "convertedModels/BIM1/BIM1841/model.glb"
    ],
    "metadataOutFiles": [
        "convertedModels/BIM1/BIM1841/model.json"
    ],
    "numCreatedGltfMeshes": 3640,
    "numCreatedMetaObjects": 3644,
    "numExportedPropertySetsOrElementQuantities": 11,
    "modelBoundsMax": [
        793.6258190000001,
        109.50886600000004,
        106.35616800000003
    ],
    "modelBoundsMin": [
        705.5118569999997,
        84.995206,
        82.08313499999997
    ]
}