{
  "id": "IfcProject",
  "projectId": "0HXpBSJeXCieb8ZCRZtdyz",
  "author": "Jon",
  "createdAt": "2014-12-09T00:27:55",
  "schema": "IFC4",
  "creatingApplication": "ggIFC - Exporter by Geometry Gym Pty Ltd",
  "metaObjects": [
    {
      "id": "0HXpBSJeXCieb8ZCRZtdyz",
      "name": "IfcProject",
      "type": "IfcProject",
      "parent": null
    },
    {
      "id": "2UrSelLcv7p8sV8DUl$XR_",
      "name": "IfcBuilding",
      "type": "IfcBuilding",
      "parent": "0HXpBSJeXCieb8ZCRZtdyz"
    },
    {
      "id": "3tkl48paX9yw0lahGPGmeU",
      "name": null,
      "type": "IfcSanitaryTerminal",
      "parent": "2UrSelLcv7p8sV8DUl$XR_"
    }
  ]
}